{
  "pais_id": "51bb19a9-e12a-40c3-884e-93b13ac9dee9",
  "sucursal_id": "c023312e-6fa7-4481-bb1c-fe9c360c3f73",
  "cutoff": "2026-05-09T00:00:00.000Z",
  "deleted_count": 49,
  "carry_cash": -1683,
  "carry_bank": -2162.5,
  "rows": [
    {
      "id": "1ac9ef7a-b32c-4c1c-ba7e-2ecb33297fce",
      "user_id": "38699080-b3d8-44a8-9863-34946a8f1617",
      "cashbox_id": "main",
      "date": "2026-04-06T12:00:00+00:00",
      "type": "income",
      "payment_method": "cash",
      "amount": 20,
      "description": "venta de 4 prendas en liquidacion",
      "created_at": "2026-04-06T19:51:26.045325+00:00",
      "sucursal_id": "c023312e-6fa7-4481-bb1c-fe9c360c3f73",
      "pais_id": "51bb19a9-e12a-40c3-884e-93b13ac9dee9"
    },
    {
      "id": "345d4880-1f85-4e6d-a0a3-45fbd9f74244",
      "user_id": "38699080-b3d8-44a8-9863-34946a8f1617",
      "cashbox_id": "main",
      "date": "2026-04-06T12:00:00+00:00",
      "type": "expense",
      "payment_method": "qr",
      "amount": 32,
      "description": "Comida",
      "created_at": "2026-04-06T20:53:05.123129+00:00",
      "sucursal_id": "c023312e-6fa7-4481-bb1c-fe9c360c3f73",
      "pais_id": "51bb19a9-e12a-40c3-884e-93b13ac9dee9"
    },
    {
      "id": "c8196481-e984-4e8c-abc7-e5dc605d40bf",
      "user_id": "38699080-b3d8-44a8-9863-34946a8f1617",
      "cashbox_id": "main",
      "date": "2026-04-06T12:00:00+00:00",
      "type": "expense",
      "payment_method": "cash",
      "amount": 7,
      "description": "Envio Lentes Vintage",
      "created_at": "2026-04-06T19:45:37.326305+00:00",
      "sucursal_id": "c023312e-6fa7-4481-bb1c-fe9c360c3f73",
      "pais_id": "51bb19a9-e12a-40c3-884e-93b13ac9dee9"
    },
    {
      "id": "0d6af750-7d26-4222-a11c-3b55261c31ff",
      "user_id": "38699080-b3d8-44a8-9863-34946a8f1617",
      "cashbox_id": "main",
      "date": "2026-04-06T12:00:00+00:00",
      "type": "income",
      "payment_method": "cash",
      "amount": 40,
      "description": "2-ropa",
      "created_at": "2026-04-06T23:59:18.01567+00:00",
      "sucursal_id": "c023312e-6fa7-4481-bb1c-fe9c360c3f73",
      "pais_id": "51bb19a9-e12a-40c3-884e-93b13ac9dee9"
    },
    {
      "id": "2a068896-54ea-4e7a-bdd9-20083fc97ec8",
      "user_id": "38699080-b3d8-44a8-9863-34946a8f1617",
      "cashbox_id": "main",
      "date": "2026-04-07T12:00:00+00:00",
      "type": "income",
      "payment_method": "cash",
      "amount": 35,
      "description": "2 aretes",
      "created_at": "2026-04-07T15:49:09.320653+00:00",
      "sucursal_id": "c023312e-6fa7-4481-bb1c-fe9c360c3f73",
      "pais_id": "51bb19a9-e12a-40c3-884e-93b13ac9dee9"
    },
    {
      "id": "ef5a430d-4d08-47cd-9850-e0557886ee74",
      "user_id": "38699080-b3d8-44a8-9863-34946a8f1617",
      "cashbox_id": "main",
      "date": "2026-04-07T12:00:00+00:00",
      "type": "income",
      "payment_method": "cash",
      "amount": 60,
      "description": "Venta de 3 Polos",
      "created_at": "2026-04-07T15:49:00.239962+00:00",
      "sucursal_id": "c023312e-6fa7-4481-bb1c-fe9c360c3f73",
      "pais_id": "51bb19a9-e12a-40c3-884e-93b13ac9dee9"
    },
    {
      "id": "906f88ec-5a4f-4715-ad58-67d9ab6c736e",
      "user_id": "62676dc6-c93d-46d1-a863-5ff0c00049a9",
      "cashbox_id": "main",
      "date": "2026-04-07T12:00:00+00:00",
      "type": "expense",
      "payment_method": "cash",
      "amount": 200,
      "description": "SHAMPOO Y FLOTADOR DE AGUA",
      "created_at": "2026-04-07T21:07:05.022088+00:00",
      "sucursal_id": "c023312e-6fa7-4481-bb1c-fe9c360c3f73",
      "pais_id": "51bb19a9-e12a-40c3-884e-93b13ac9dee9"
    },
    {
      "id": "71b64423-9311-4232-83a5-626cf624eeeb",
      "user_id": "62676dc6-c93d-46d1-a863-5ff0c00049a9",
      "cashbox_id": "main",
      "date": "2026-04-07T12:00:00+00:00",
      "type": "income",
      "payment_method": "qr",
      "amount": 100,
      "description": "5 prendas",
      "created_at": "2026-04-07T19:23:20.245506+00:00",
      "sucursal_id": "c023312e-6fa7-4481-bb1c-fe9c360c3f73",
      "pais_id": "51bb19a9-e12a-40c3-884e-93b13ac9dee9"
    },
    {
      "id": "21697912-f6c6-41f9-be6f-0a79dc98ebb4",
      "user_id": "38699080-b3d8-44a8-9863-34946a8f1617",
      "cashbox_id": "main",
      "date": "2026-04-07T12:00:00+00:00",
      "type": "income",
      "payment_method": "qr",
      "amount": 60,
      "description": "venta de ropa",
      "created_at": "2026-04-07T15:49:20.472376+00:00",
      "sucursal_id": "c023312e-6fa7-4481-bb1c-fe9c360c3f73",
      "pais_id": "51bb19a9-e12a-40c3-884e-93b13ac9dee9"
    },
    {
      "id": "6c94470c-30b4-4cb5-9e82-24189e42a362",
      "user_id": "38699080-b3d8-44a8-9863-34946a8f1617",
      "cashbox_id": "main",
      "date": "2026-04-08T12:00:00+00:00",
      "type": "income",
      "payment_method": "cash",
      "amount": 5,
      "description": "liquidacion",
      "created_at": "2026-04-08T23:57:53.279515+00:00",
      "sucursal_id": "c023312e-6fa7-4481-bb1c-fe9c360c3f73",
      "pais_id": "51bb19a9-e12a-40c3-884e-93b13ac9dee9"
    },
    {
      "id": "072bfe9d-d59a-43d8-922f-1a82124c569d",
      "user_id": "62676dc6-c93d-46d1-a863-5ff0c00049a9",
      "cashbox_id": "main",
      "date": "2026-04-08T12:00:00+00:00",
      "type": "expense",
      "payment_method": "qr",
      "amount": 48,
      "description": "faltante de flotador",
      "created_at": "2026-04-08T23:04:28.460225+00:00",
      "sucursal_id": "c023312e-6fa7-4481-bb1c-fe9c360c3f73",
      "pais_id": "51bb19a9-e12a-40c3-884e-93b13ac9dee9"
    },
    {
      "id": "64b569f5-98d7-4451-be9c-3506302ff60a",
      "user_id": "62676dc6-c93d-46d1-a863-5ff0c00049a9",
      "cashbox_id": "main",
      "date": "2026-04-08T12:00:00+00:00",
      "type": "income",
      "payment_method": "cash",
      "amount": 180,
      "description": "1 lente que no esta registrado, 6 polos",
      "created_at": "2026-04-08T23:04:06.225333+00:00",
      "sucursal_id": "c023312e-6fa7-4481-bb1c-fe9c360c3f73",
      "pais_id": "51bb19a9-e12a-40c3-884e-93b13ac9dee9"
    },
    {
      "id": "8aa29393-5a39-4545-b6f1-01bf17c832ee",
      "user_id": "38699080-b3d8-44a8-9863-34946a8f1617",
      "cashbox_id": "main",
      "date": "2026-04-10T12:00:00+00:00",
      "type": "income",
      "payment_method": "qr",
      "amount": 40,
      "description": "2 polos",
      "created_at": "2026-04-10T23:00:58.382858+00:00",
      "sucursal_id": "c023312e-6fa7-4481-bb1c-fe9c360c3f73",
      "pais_id": "51bb19a9-e12a-40c3-884e-93b13ac9dee9"
    },
    {
      "id": "d29cc9f5-d6e9-49c3-a816-388998e60147",
      "user_id": "38699080-b3d8-44a8-9863-34946a8f1617",
      "cashbox_id": "main",
      "date": "2026-04-10T12:00:00+00:00",
      "type": "expense",
      "payment_method": "cash",
      "amount": 65,
      "description": "vinilo textil",
      "created_at": "2026-04-10T23:13:31.445639+00:00",
      "sucursal_id": "c023312e-6fa7-4481-bb1c-fe9c360c3f73",
      "pais_id": "51bb19a9-e12a-40c3-884e-93b13ac9dee9"
    },
    {
      "id": "eb8e2083-ab66-4fa9-8091-5a1e3ea76b0f",
      "user_id": "38699080-b3d8-44a8-9863-34946a8f1617",
      "cashbox_id": "main",
      "date": "2026-04-10T12:00:00+00:00",
      "type": "expense",
      "payment_method": "cash",
      "amount": 370,
      "description": "poleras",
      "created_at": "2026-04-10T23:13:16.394837+00:00",
      "sucursal_id": "c023312e-6fa7-4481-bb1c-fe9c360c3f73",
      "pais_id": "51bb19a9-e12a-40c3-884e-93b13ac9dee9"
    },
    {
      "id": "369ffcb5-2862-4922-abe9-b64151457c71",
      "user_id": "38699080-b3d8-44a8-9863-34946a8f1617",
      "cashbox_id": "main",
      "date": "2026-04-10T12:00:00+00:00",
      "type": "income",
      "payment_method": "cash",
      "amount": 5,
      "description": "1 gogo",
      "created_at": "2026-04-10T23:12:39.882621+00:00",
      "sucursal_id": "c023312e-6fa7-4481-bb1c-fe9c360c3f73",
      "pais_id": "51bb19a9-e12a-40c3-884e-93b13ac9dee9"
    },
    {
      "id": "75a66b59-72eb-4a1d-8a4d-1e2c58a32a68",
      "user_id": "38699080-b3d8-44a8-9863-34946a8f1617",
      "cashbox_id": "main",
      "date": "2026-04-10T12:00:00+00:00",
      "type": "income",
      "payment_method": "cash",
      "amount": 40,
      "description": "aretes",
      "created_at": "2026-04-10T23:12:50.122609+00:00",
      "sucursal_id": "c023312e-6fa7-4481-bb1c-fe9c360c3f73",
      "pais_id": "51bb19a9-e12a-40c3-884e-93b13ac9dee9"
    },
    {
      "id": "6f865b88-4654-491e-ab68-5d22a1598212",
      "user_id": "38699080-b3d8-44a8-9863-34946a8f1617",
      "cashbox_id": "main",
      "date": "2026-04-10T12:00:00+00:00",
      "type": "income",
      "payment_method": "qr",
      "amount": 10,
      "description": "1 arete",
      "created_at": "2026-04-10T23:12:26.838731+00:00",
      "sucursal_id": "c023312e-6fa7-4481-bb1c-fe9c360c3f73",
      "pais_id": "51bb19a9-e12a-40c3-884e-93b13ac9dee9"
    },
    {
      "id": "93aee510-4eca-4f3f-b160-2bbcb5a96a92",
      "user_id": "38699080-b3d8-44a8-9863-34946a8f1617",
      "cashbox_id": "main",
      "date": "2026-04-10T12:00:00+00:00",
      "type": "expense",
      "payment_method": "qr",
      "amount": 150,
      "description": "dtf y polera",
      "created_at": "2026-04-10T23:12:15.404813+00:00",
      "sucursal_id": "c023312e-6fa7-4481-bb1c-fe9c360c3f73",
      "pais_id": "51bb19a9-e12a-40c3-884e-93b13ac9dee9"
    },
    {
      "id": "9e572ccc-f788-47e5-afb5-c0af075b097b",
      "user_id": "38699080-b3d8-44a8-9863-34946a8f1617",
      "cashbox_id": "main",
      "date": "2026-04-11T00:00:00+00:00",
      "type": "expense",
      "payment_method": "qr",
      "amount": 100,
      "description": "banco y comida",
      "created_at": "2026-04-11T15:59:48.439751+00:00",
      "sucursal_id": "c023312e-6fa7-4481-bb1c-fe9c360c3f73",
      "pais_id": "51bb19a9-e12a-40c3-884e-93b13ac9dee9"
    },
    {
      "id": "38148c49-a8aa-4f5f-bad4-e3284e1d612b",
      "user_id": "38699080-b3d8-44a8-9863-34946a8f1617",
      "cashbox_id": "main",
      "date": "2026-04-11T12:00:00+00:00",
      "type": "income",
      "payment_method": "cash",
      "amount": 350,
      "description": "Ropa",
      "created_at": "2026-04-11T18:43:38.567094+00:00",
      "sucursal_id": "c023312e-6fa7-4481-bb1c-fe9c360c3f73",
      "pais_id": "51bb19a9-e12a-40c3-884e-93b13ac9dee9"
    },
    {
      "id": "c91bb744-7b8a-4304-8acc-0e54d0f3b376",
      "user_id": "38699080-b3d8-44a8-9863-34946a8f1617",
      "cashbox_id": "main",
      "date": "2026-04-11T12:00:00+00:00",
      "type": "income",
      "payment_method": "cash",
      "amount": 40,
      "description": "pirañas",
      "created_at": "2026-04-11T18:43:49.040545+00:00",
      "sucursal_id": "c023312e-6fa7-4481-bb1c-fe9c360c3f73",
      "pais_id": "51bb19a9-e12a-40c3-884e-93b13ac9dee9"
    },
    {
      "id": "2d6eb24e-6f3d-49fb-a766-87bd4ad2336b",
      "user_id": "38699080-b3d8-44a8-9863-34946a8f1617",
      "cashbox_id": "main",
      "date": "2026-04-13T12:00:00+00:00",
      "type": "income",
      "payment_method": "qr",
      "amount": 30,
      "description": "",
      "created_at": "2026-04-13T23:35:19.777512+00:00",
      "sucursal_id": "c023312e-6fa7-4481-bb1c-fe9c360c3f73",
      "pais_id": "51bb19a9-e12a-40c3-884e-93b13ac9dee9"
    },
    {
      "id": "f5cd3df5-2b57-4191-a253-055c717e88f5",
      "user_id": "38699080-b3d8-44a8-9863-34946a8f1617",
      "cashbox_id": "main",
      "date": "2026-04-13T12:00:00+00:00",
      "type": "income",
      "payment_method": "cash",
      "amount": 75,
      "description": "ropa",
      "created_at": "2026-04-13T15:26:30.769659+00:00",
      "sucursal_id": "c023312e-6fa7-4481-bb1c-fe9c360c3f73",
      "pais_id": "51bb19a9-e12a-40c3-884e-93b13ac9dee9"
    },
    {
      "id": "0dbad5f9-376c-4047-a712-cf9be09d37ea",
      "user_id": "38699080-b3d8-44a8-9863-34946a8f1617",
      "cashbox_id": "main",
      "date": "2026-04-13T12:00:00+00:00",
      "type": "income",
      "payment_method": "cash",
      "amount": 30,
      "description": "1 polo",
      "created_at": "2026-04-13T16:05:35.529591+00:00",
      "sucursal_id": "c023312e-6fa7-4481-bb1c-fe9c360c3f73",
      "pais_id": "51bb19a9-e12a-40c3-884e-93b13ac9dee9"
    },
    {
      "id": "6b187262-5791-4bcf-9309-5b612950dbe6",
      "user_id": "38699080-b3d8-44a8-9863-34946a8f1617",
      "cashbox_id": "main",
      "date": "2026-04-13T12:00:00+00:00",
      "type": "income",
      "payment_method": "qr",
      "amount": 90,
      "description": "3 polos",
      "created_at": "2026-04-13T16:18:54.916858+00:00",
      "sucursal_id": "c023312e-6fa7-4481-bb1c-fe9c360c3f73",
      "pais_id": "51bb19a9-e12a-40c3-884e-93b13ac9dee9"
    },
    {
      "id": "d4397b14-ce19-4b5a-a4c7-1822534163ea",
      "user_id": "62676dc6-c93d-46d1-a863-5ff0c00049a9",
      "cashbox_id": "main",
      "date": "2026-04-13T12:00:00+00:00",
      "type": "income",
      "payment_method": "cash",
      "amount": 20,
      "description": "1 top",
      "created_at": "2026-04-13T20:41:31.383115+00:00",
      "sucursal_id": "c023312e-6fa7-4481-bb1c-fe9c360c3f73",
      "pais_id": "51bb19a9-e12a-40c3-884e-93b13ac9dee9"
    },
    {
      "id": "836a356a-fff3-48b0-b6b3-7eb6b2acbef6",
      "user_id": "38699080-b3d8-44a8-9863-34946a8f1617",
      "cashbox_id": "main",
      "date": "2026-04-13T12:00:00+00:00",
      "type": "expense",
      "payment_method": "qr",
      "amount": 70,
      "description": "prime",
      "created_at": "2026-04-13T23:32:25.063524+00:00",
      "sucursal_id": "c023312e-6fa7-4481-bb1c-fe9c360c3f73",
      "pais_id": "51bb19a9-e12a-40c3-884e-93b13ac9dee9"
    },
    {
      "id": "62460374-2224-4ed6-b2d3-d24bd1df1a9e",
      "user_id": "38699080-b3d8-44a8-9863-34946a8f1617",
      "cashbox_id": "main",
      "date": "2026-04-13T12:00:00+00:00",
      "type": "expense",
      "payment_method": "qr",
      "amount": 32.5,
      "description": "",
      "created_at": "2026-04-13T23:34:38.988154+00:00",
      "sucursal_id": "c023312e-6fa7-4481-bb1c-fe9c360c3f73",
      "pais_id": "51bb19a9-e12a-40c3-884e-93b13ac9dee9"
    },
    {
      "id": "b5c92aa7-92bd-4c41-8c7a-ac27b26e4471",
      "user_id": "38699080-b3d8-44a8-9863-34946a8f1617",
      "cashbox_id": "main",
      "date": "2026-04-14T12:00:00+00:00",
      "type": "expense",
      "payment_method": "cash",
      "amount": 20,
      "description": "donas",
      "created_at": "2026-04-14T23:57:45.217555+00:00",
      "sucursal_id": "c023312e-6fa7-4481-bb1c-fe9c360c3f73",
      "pais_id": "51bb19a9-e12a-40c3-884e-93b13ac9dee9"
    },
    {
      "id": "4b80b2b8-c16b-49e7-875d-f103d9730be7",
      "user_id": "38699080-b3d8-44a8-9863-34946a8f1617",
      "cashbox_id": "main",
      "date": "2026-04-14T12:00:00+00:00",
      "type": "income",
      "payment_method": "cash",
      "amount": 95,
      "description": "Ropa Y aretes",
      "created_at": "2026-04-14T23:57:37.383967+00:00",
      "sucursal_id": "c023312e-6fa7-4481-bb1c-fe9c360c3f73",
      "pais_id": "51bb19a9-e12a-40c3-884e-93b13ac9dee9"
    },
    {
      "id": "08a03440-9f57-45cf-9462-07ce6c8c4ffc",
      "user_id": "38699080-b3d8-44a8-9863-34946a8f1617",
      "cashbox_id": "main",
      "date": "2026-04-15T12:00:00+00:00",
      "type": "income",
      "payment_method": "cash",
      "amount": 40,
      "description": "2 polos",
      "created_at": "2026-04-16T12:57:06.905652+00:00",
      "sucursal_id": "c023312e-6fa7-4481-bb1c-fe9c360c3f73",
      "pais_id": "51bb19a9-e12a-40c3-884e-93b13ac9dee9"
    },
    {
      "id": "de7b5ff7-c272-42c6-87af-40e3d9040b78",
      "user_id": "38699080-b3d8-44a8-9863-34946a8f1617",
      "cashbox_id": "main",
      "date": "2026-04-15T12:00:00+00:00",
      "type": "income",
      "payment_method": "cash",
      "amount": 25,
      "description": "cinta termica",
      "created_at": "2026-04-16T12:58:22.383505+00:00",
      "sucursal_id": "c023312e-6fa7-4481-bb1c-fe9c360c3f73",
      "pais_id": "51bb19a9-e12a-40c3-884e-93b13ac9dee9"
    },
    {
      "id": "e346ccda-1cff-4dee-9a14-e106fffaaf0b",
      "user_id": "38699080-b3d8-44a8-9863-34946a8f1617",
      "cashbox_id": "main",
      "date": "2026-04-15T12:00:00+00:00",
      "type": "income",
      "payment_method": "qr",
      "amount": 30,
      "description": "Cinta termica",
      "created_at": "2026-04-16T12:58:13.070401+00:00",
      "sucursal_id": "c023312e-6fa7-4481-bb1c-fe9c360c3f73",
      "pais_id": "51bb19a9-e12a-40c3-884e-93b13ac9dee9"
    },
    {
      "id": "156790b8-45f8-4438-8151-9b82a5f28d4b",
      "user_id": "38699080-b3d8-44a8-9863-34946a8f1617",
      "cashbox_id": "main",
      "date": "2026-04-15T12:00:00+00:00",
      "type": "income",
      "payment_method": "cash",
      "amount": 25,
      "description": "ropa liquidacion",
      "created_at": "2026-04-16T12:57:40.075816+00:00",
      "sucursal_id": "c023312e-6fa7-4481-bb1c-fe9c360c3f73",
      "pais_id": "51bb19a9-e12a-40c3-884e-93b13ac9dee9"
    },
    {
      "id": "7c973c51-a89f-4bed-a50a-d92950e93f43",
      "user_id": "38699080-b3d8-44a8-9863-34946a8f1617",
      "cashbox_id": "main",
      "date": "2026-04-16T12:00:00+00:00",
      "type": "income",
      "payment_method": "cash",
      "amount": 20,
      "description": "1 polo",
      "created_at": "2026-04-16T14:02:09.195868+00:00",
      "sucursal_id": "c023312e-6fa7-4481-bb1c-fe9c360c3f73",
      "pais_id": "51bb19a9-e12a-40c3-884e-93b13ac9dee9"
    },
    {
      "id": "ec76933d-28df-42c7-a116-2627f8dc3600",
      "user_id": "38699080-b3d8-44a8-9863-34946a8f1617",
      "cashbox_id": "main",
      "date": "2026-04-25T12:00:00+00:00",
      "type": "income",
      "payment_method": "cash",
      "amount": 60,
      "description": "lente",
      "created_at": "2026-04-25T22:14:04.391716+00:00",
      "sucursal_id": "c023312e-6fa7-4481-bb1c-fe9c360c3f73",
      "pais_id": "51bb19a9-e12a-40c3-884e-93b13ac9dee9"
    },
    {
      "id": "ea42a1af-7b62-4cd5-a79d-825d86cd9c8a",
      "user_id": "38699080-b3d8-44a8-9863-34946a8f1617",
      "cashbox_id": "main",
      "date": "2026-04-25T12:00:00+00:00",
      "type": "income",
      "payment_method": "cash",
      "amount": 100,
      "description": "chompas",
      "created_at": "2026-04-25T22:13:30.14209+00:00",
      "sucursal_id": "c023312e-6fa7-4481-bb1c-fe9c360c3f73",
      "pais_id": "51bb19a9-e12a-40c3-884e-93b13ac9dee9"
    },
    {
      "id": "cd19b8ce-1423-4012-b445-2973fc993aac",
      "user_id": "38699080-b3d8-44a8-9863-34946a8f1617",
      "cashbox_id": "main",
      "date": "2026-04-25T12:00:00+00:00",
      "type": "income",
      "payment_method": "cash",
      "amount": 120,
      "description": "chompas",
      "created_at": "2026-04-25T22:13:18.953121+00:00",
      "sucursal_id": "c023312e-6fa7-4481-bb1c-fe9c360c3f73",
      "pais_id": "51bb19a9-e12a-40c3-884e-93b13ac9dee9"
    },
    {
      "id": "39390013-3681-42b8-bb39-3f7c0bc2d0bc",
      "user_id": "38699080-b3d8-44a8-9863-34946a8f1617",
      "cashbox_id": "main",
      "date": "2026-04-26T12:00:00+00:00",
      "type": "income",
      "payment_method": "qr",
      "amount": 40,
      "description": "polera",
      "created_at": "2026-04-26T21:36:31.727704+00:00",
      "sucursal_id": "c023312e-6fa7-4481-bb1c-fe9c360c3f73",
      "pais_id": "51bb19a9-e12a-40c3-884e-93b13ac9dee9"
    },
    {
      "id": "dd29f6b2-2eb2-4325-8556-6129da6a7479",
      "user_id": "38699080-b3d8-44a8-9863-34946a8f1617",
      "cashbox_id": "main",
      "date": "2026-04-26T12:00:00+00:00",
      "type": "expense",
      "payment_method": "qr",
      "amount": 1490,
      "description": "Banco fie",
      "created_at": "2026-04-26T20:59:38.245762+00:00",
      "sucursal_id": "c023312e-6fa7-4481-bb1c-fe9c360c3f73",
      "pais_id": "51bb19a9-e12a-40c3-884e-93b13ac9dee9"
    },
    {
      "id": "d0ea56c0-4e06-4efd-b377-07736bd63525",
      "user_id": "38699080-b3d8-44a8-9863-34946a8f1617",
      "cashbox_id": "main",
      "date": "2026-04-27T12:00:00+00:00",
      "type": "expense",
      "payment_method": "qr",
      "amount": 690,
      "description": "banco fie vinilos",
      "created_at": "2026-04-27T20:20:56.02572+00:00",
      "sucursal_id": "c023312e-6fa7-4481-bb1c-fe9c360c3f73",
      "pais_id": "51bb19a9-e12a-40c3-884e-93b13ac9dee9"
    },
    {
      "id": "4e1d8010-961e-43c7-8910-f31b061e8511",
      "user_id": "38699080-b3d8-44a8-9863-34946a8f1617",
      "cashbox_id": "main",
      "date": "2026-04-27T12:00:00+00:00",
      "type": "expense",
      "payment_method": "cash",
      "amount": 2506,
      "description": "pagos alquiler, internet etc",
      "created_at": "2026-04-27T19:59:57.344754+00:00",
      "sucursal_id": "c023312e-6fa7-4481-bb1c-fe9c360c3f73",
      "pais_id": "51bb19a9-e12a-40c3-884e-93b13ac9dee9"
    },
    {
      "id": "1081f938-cffd-4b53-9270-820ddd89bba5",
      "user_id": "62676dc6-c93d-46d1-a863-5ff0c00049a9",
      "cashbox_id": "main",
      "date": "2026-04-28T00:00:00+00:00",
      "type": "income",
      "payment_method": "qr",
      "amount": 90,
      "description": "ROPA",
      "created_at": "2026-04-28T23:05:00.470645+00:00",
      "sucursal_id": "c023312e-6fa7-4481-bb1c-fe9c360c3f73",
      "pais_id": "51bb19a9-e12a-40c3-884e-93b13ac9dee9"
    },
    {
      "id": "3c4c57e8-edef-49b8-8371-71241ce17096",
      "user_id": "62676dc6-c93d-46d1-a863-5ff0c00049a9",
      "cashbox_id": "main",
      "date": "2026-04-28T12:00:00+00:00",
      "type": "income",
      "payment_method": "cash",
      "amount": 80,
      "description": "ROPA",
      "created_at": "2026-04-28T22:32:41.378381+00:00",
      "sucursal_id": "c023312e-6fa7-4481-bb1c-fe9c360c3f73",
      "pais_id": "51bb19a9-e12a-40c3-884e-93b13ac9dee9"
    },
    {
      "id": "02eda27e-e6e4-487a-908d-e9780360ef6d",
      "user_id": "62676dc6-c93d-46d1-a863-5ff0c00049a9",
      "cashbox_id": "main",
      "date": "2026-04-28T12:00:00+00:00",
      "type": "income",
      "payment_method": "qr",
      "amount": 70,
      "description": "ropa y lentes",
      "created_at": "2026-04-28T22:02:26.189907+00:00",
      "sucursal_id": "c023312e-6fa7-4481-bb1c-fe9c360c3f73",
      "pais_id": "51bb19a9-e12a-40c3-884e-93b13ac9dee9"
    },
    {
      "id": "2381f5b4-cc62-464b-9ff4-535892749cbc",
      "user_id": "62676dc6-c93d-46d1-a863-5ff0c00049a9",
      "cashbox_id": "main",
      "date": "2026-04-29T12:00:00+00:00",
      "type": "expense",
      "payment_method": "qr",
      "amount": 200,
      "description": "gasolina",
      "created_at": "2026-04-29T21:13:33.937364+00:00",
      "sucursal_id": "c023312e-6fa7-4481-bb1c-fe9c360c3f73",
      "pais_id": "51bb19a9-e12a-40c3-884e-93b13ac9dee9"
    },
    {
      "id": "86193ca6-788f-492b-8663-3d6827bd1d4e",
      "user_id": "62676dc6-c93d-46d1-a863-5ff0c00049a9",
      "cashbox_id": "main",
      "date": "2026-04-30T12:00:00+00:00",
      "type": "income",
      "payment_method": "qr",
      "amount": 90,
      "description": "",
      "created_at": "2026-04-30T00:20:43.872215+00:00",
      "sucursal_id": "c023312e-6fa7-4481-bb1c-fe9c360c3f73",
      "pais_id": "51bb19a9-e12a-40c3-884e-93b13ac9dee9"
    },
    {
      "id": "97935544-45c5-48e0-8afd-9d0e88f68dfd",
      "user_id": "38699080-b3d8-44a8-9863-34946a8f1617",
      "cashbox_id": "main",
      "date": "2026-05-02T12:00:00+00:00",
      "type": "income",
      "payment_method": "cash",
      "amount": 20,
      "description": "POLO",
      "created_at": "2026-05-02T21:14:20.428724+00:00",
      "sucursal_id": "c023312e-6fa7-4481-bb1c-fe9c360c3f73",
      "pais_id": "51bb19a9-e12a-40c3-884e-93b13ac9dee9"
    }
  ]
}